CHANGES.txt
CREDITS.txt
README.txt
bootstrap.py
buildout.cfg
setup.cfg
setup.py
docs/LICENSE.txt
docs/testing.txt
src/repoze/__init__.py
src/repoze.cssutils.egg-info/PKG-INFO
src/repoze.cssutils.egg-info/SOURCES.txt
src/repoze.cssutils.egg-info/dependency_links.txt
src/repoze.cssutils.egg-info/namespace_packages.txt
src/repoze.cssutils.egg-info/not-zip-safe
src/repoze.cssutils.egg-info/requires.txt
src/repoze.cssutils.egg-info/top_level.txt
src/repoze/cssutils/__init__.py
src/repoze/cssutils/css.py
src/repoze/cssutils/dom.py
src/repoze/cssutils/parser.py
src/repoze/cssutils/common/__init__.py
src/repoze/cssutils/common/path.py
src/repoze/cssutils/common/testrunner.py
src/repoze/cssutils/tests/__init__.py
src/repoze/cssutils/tests/test_css.py
src/repoze/cssutils/tests/test_css_cascade.py
src/repoze/cssutils/tests/test_css_errors.py
src/repoze/cssutils/tests/test_css_media.py
src/repoze/cssutils/tests/test_css_with_minidom.py