Metadata-Version: 1.0
Name: repoze.cssutils
Version: 1.0a6
Summary: CSS parsing and utilities
Home-page: http://www.repoze.org
Author: David Pratt
Author-email: repoze-dev@lists.repoze.org
License: BSD (refer to /docs/LICENSE.txt)
Keywords: css repoze parsing
Platform: UNKNOWN
Classifier: Development Status :: 3 - Alpha
Classifier: Intended Audience :: Developers
Classifier: Programming Language :: Python
Classifier: Topic :: Internet :: WWW/HTTP
Classifier: Topic :: Internet :: WWW/HTTP :: Dynamic Content
Classifier: Topic :: Software Development :: Libraries :: Python Modules
